preflightpy/__init__.py
preflightpy/env.py
preflightpy/params.py
preflightpy/system.py
preflightpy-0.6.2.dist-info/LICENSE
preflightpy-0.6.2.dist-info/METADATA
preflightpy-0.6.2.dist-info/WHEEL
preflightpy-0.6.2.dist-info/top_level.txt
preflightpy-0.6.2.dist-info/RECORD
