Metadata-Version: 2.1
Name: preflightpy
Version: 0.6.2
Summary: Python package for rocket flight simulation.
Home-page: UNKNOWN
Author: Oxyde2
Author-email: iorbital.projects@gmail.com
License: UNKNOWN
Project-URL: Bug Reports, https://github.com/Oxyde2/Preflight/issues
Project-URL: Funding, https://www.gofundme.com/f/quark-suborbital
Project-URL: Source, https://github.com/Oxyde2/Preflight
Keywords: model rocketry,rocketry,flight,simulator
Platform: UNKNOWN
Classifier: Development Status :: 3 - Alpha
Classifier: Intended Audience :: Science/Research
Classifier: Topic :: Scientific/Engineering :: Atmospheric Science
Classifier: License :: OSI Approved :: GNU General Public License v3 or later (GPLv3+)
Classifier: Programming Language :: Python :: 3
Classifier: Programming Language :: Python :: 3.6
Classifier: Programming Language :: Python :: 3.7
Requires-Python: >=3.6, <4
Requires-Dist: matplotlib
Provides-Extra: dev
Requires-Dist: check-manifest ; extra == 'dev'
Requires-Dist: flake8 ; extra == 'dev'
Provides-Extra: test
Requires-Dist: coverage ; extra == 'test'
Requires-Dist: pytest ; extra == 'test'
Requires-Dist: pytest-cov ; extra == 'test'
Requires-Dist: coveralls ; extra == 'test'
Requires-Dist: pyyaml ; extra == 'test'
